fmcmcpkd/__init__.py
fmcmcpkd/server.py
fmcmcpkd-0.3.0.dist-info/METADATA
fmcmcpkd-0.3.0.dist-info/WHEEL
fmcmcpkd-0.3.0.dist-info/entry_points.txt
fmcmcpkd-0.3.0.dist-info/top_level.txt
fmcmcpkd-0.3.0.dist-info/RECORD
