Metadata-Version: 2.4
Name: fmcmcpkd
Version: 0.3.0
Summary: An MCP server exposing FMC text output via stdio
Author: Your Name
Requires-Python: >=3.9
Requires-Dist: mcp
